pyhouse/__init__.py
pyhouse/py.typed
pyhouse/datalake/__init__.py
pyhouse/datalake/data_link.py
pyhouse/datalake/file_system_data_link.py
pyhouse/datalake/hive_data_link.py
pyhouse/datalake/in_memory_datalink.py
pyhouse/datalake/jdbc_data_link.py
pyhouse/datalake/kafka_data_link.py
pyhouse/datalake/path_based_data_link.py
pyhouse/datalake/snowflake_data_link.py
pyhouse/paramstore/__init__.py
pyhouse/paramstore/aws_parameter_store.py
pyhouse/paramstore/file_parameter_store.py
pyhouse/paramstore/parameter_store.py
pyhouse/spark/__init__.py
pyhouse/spark/spark_sessions.py
pyhouse-0.0.13.dist-info/LICENSE.txt
pyhouse-0.0.13.dist-info/METADATA
pyhouse-0.0.13.dist-info/WHEEL
pyhouse-0.0.13.dist-info/top_level.txt
pyhouse-0.0.13.dist-info/RECORD
