Metadata-Version: 2.1
Name: pyhouse
Version: 0.0.13
Summary: Lighthouse for Python: a package facilitating the creation of data pipelines.
Home-page: https://www.dataminded.be
Author: Data Minded
Author-email: dev@dataminded.be
License: Apache-2.0
Keywords: data lake engineering pipeline catalog cloud
Platform: UNKNOWN
Classifier: Development Status :: 5 - Production/Stable
Classifier: Intended Audience :: Developers
Classifier: Topic :: Software Development :: Libraries
Classifier: License :: OSI Approved :: Apache Software License
Classifier: Programming Language :: Python :: 3.7
Requires-Dist: boto3 (>=1.4.4)
